obm/__init__.py
obm/mixins.py
obm/models.py
obm/serializers.py
obm/sync.py
obm/utils.py
obm/connectors/__init__.py
obm/connectors/base.py
obm/connectors/bitcoin.py
obm/connectors/ethereum.py
obm/connectors/exceptions.py
obm-0.0.5.dist-info/AUTHORS
obm-0.0.5.dist-info/LICENSE
obm-0.0.5.dist-info/METADATA
obm-0.0.5.dist-info/WHEEL
obm-0.0.5.dist-info/top_level.txt
obm-0.0.5.dist-info/RECORD
