Metadata-Version: 2.1
Name: obm
Version: 0.0.5
Summary: Async blockchain nodes interacting tool with ORM-like api.
Home-page: https://github.com/madnesspie/obm
Author: Alexander Polishchuk
Author-email: apolishchuk52@gmail.com
License: GNU Lesser General Public License v3 or later (LGPLv3+)
Platform: UNKNOWN
Classifier: Environment :: Web Environment
Classifier: Intended Audience :: Developers
Classifier: License :: OSI Approved :: GNU Lesser General Public License v3 or later (LGPLv3+)
Classifier: Operating System :: OS Independent
Classifier: Programming Language :: Python
Classifier: Programming Language :: Python :: 3.8
Classifier: Programming Language :: Python :: 3 :: Only
Requires-Dist: aiohttp (<4,>=3.6)
Requires-Dist: web3 (<6,>=5.7)
Requires-Dist: marshmallow (<4,>=3.5)
Provides-Extra: dev
Requires-Dist: sphinx (<3,>=2.4) ; extra == 'dev'
Requires-Dist: sphinx-rtd-theme ; extra == 'dev'
Requires-Dist: python-dotenv ; extra == 'dev'
Requires-Dist: pytest ; extra == 'dev'
Requires-Dist: pylint ; extra == 'dev'
Requires-Dist: mypy ; extra == 'dev'
Requires-Dist: rope ; extra == 'dev'
